chatproto/__init__.py
chatproto/hf_apply.py
chatproto/registry.py
chatproto/conversation/__init__.py
chatproto/conversation/history.py
chatproto/conversation/settings.py
chatproto/conversation/models/__init__.py
chatproto/conversation/models/airoboros.py
chatproto/conversation/models/alpaca.py
chatproto/conversation/models/baichuan.py
chatproto/conversation/models/baize.py
chatproto/conversation/models/bard.py
chatproto/conversation/models/billa.py
chatproto/conversation/models/chatglm.py
chatproto/conversation/models/chatgpt.py
chatproto/conversation/models/claude.py
chatproto/conversation/models/cutegpt.py
chatproto/conversation/models/deepseek.py
chatproto/conversation/models/dolly.py
chatproto/conversation/models/falcon.py
chatproto/conversation/models/firefly.py
chatproto/conversation/models/h2ogpt.py
chatproto/conversation/models/internlm.py
chatproto/conversation/models/koala.py
chatproto/conversation/models/llama.py
chatproto/conversation/models/mistral.py
chatproto/conversation/models/mpt.py
chatproto/conversation/models/ningyu.py
chatproto/conversation/models/oasst_pythia.py
chatproto/conversation/models/one_shot.py
chatproto/conversation/models/openbuddy.py
chatproto/conversation/models/phoenix.py
chatproto/conversation/models/qwen.py
chatproto/conversation/models/redpajama.py
chatproto/conversation/models/rwkv.py
chatproto/conversation/models/stablelm.py
chatproto/conversation/models/starchat.py
chatproto/conversation/models/tigerbot.py
chatproto/conversation/models/vicuna.py
chatproto/conversation/models/wizardlm.py
chatproto/conversation/models/xgen.py
chatproto/conversation/models/zephyr.py
chatproto/conversation/models/zero_shot.py
chatproto-0.0.2.dist-info/LICENSE
chatproto-0.0.2.dist-info/METADATA
chatproto-0.0.2.dist-info/WHEEL
chatproto-0.0.2.dist-info/top_level.txt
chatproto-0.0.2.dist-info/RECORD
