Metadata-Version: 2.1
Name: chatproto
Version: 0.0.2
Summary: Large language model chat protocol.
Project-URL: Homepage, https://github.com/vtuber-plan/chatproto
Project-URL: Bug Tracker, https://github.com/vtuber-plan/chatproto/issues
Classifier: Programming Language :: Python :: 3
Classifier: License :: OSI Approved :: MIT License
Requires-Python: >=3.8
License-File: LICENSE
Requires-Dist: numpy
Requires-Dist: pydantic
Requires-Dist: rich >=10.0.0
Requires-Dist: shortuuid
Provides-Extra: dev
Requires-Dist: black ==23.3.0 ; extra == 'dev'
Requires-Dist: pylint ==2.8.2 ; extra == 'dev'
